xuri_rpc/__init__.py
xuri_rpc/core.py
xuri_rpc-0.2.1.dist-info/LICENSE
xuri_rpc-0.2.1.dist-info/METADATA
xuri_rpc-0.2.1.dist-info/WHEEL
xuri_rpc-0.2.1.dist-info/RECORD
