Metadata-Version: 2.3
Name: xuri-rpc
Version: 0.2.1
Summary: xuri-rpc in python
License: MIT
Author: prometheus-0017
Requires-Python: >=3.9
Classifier: License :: OSI Approved :: MIT License
Classifier: Programming Language :: Python :: 3
Classifier: Programming Language :: Python :: 3.9
Classifier: Programming Language :: Python :: 3.10
Classifier: Programming Language :: Python :: 3.11
Classifier: Programming Language :: Python :: 3.12
Classifier: Programming Language :: Python :: 3.13
Requires-Dist: typeguard (>=4.4.4,<5.0.0)
